abstra_runtimes/__init__.py
abstra_runtimes/broker.py
abstra_runtimes/dashes.py
abstra_runtimes/hf.py
abstra_runtimes/overloads.py
abstra_runtimes/utils.py
abstra_runtimes/version.py
abstra_runtimes-1.2.3.dist-info/METADATA
abstra_runtimes-1.2.3.dist-info/WHEEL
abstra_runtimes-1.2.3.dist-info/top_level.txt
abstra_runtimes-1.2.3.dist-info/RECORD
