Metadata-Version: 2.1
Name: abstra-runtimes
Version: 1.2.3
Summary: Abstra Runtimes Lib
Home-page: https://github.com/abstra-app/abstra-runtimes-lib
License: MIT
Platform: UNKNOWN
Requires-Dist: setuptools
Requires-Dist: websockets
Requires-Dist: hackerforms
Requires-Dist: abstra
Requires-Dist: fire
